Workbook

Sheet Exercise
A2: Blue Ridge Digital LLC — Income Statement Practice
A4: Reporting period | C4: Month ended December 31, 2026
A6: Task
A7: Use the five source tabs to prepare an income statement for December 2026.
A8: Use actual recognized revenue and actual expenses only.
A9: Exclude assets, liabilities, equity accounts, owner distributions, and budget figures.
A10: Show revenue, expenses, total expenses, and net income.
A12: Description | B12: Amount | C12: Totals | D12: Notes
A13: Revenue
A14: =revenue!B2 -> Harbor Dental Group | B14: =revenue!C2 -> 48000 | D14: =revenue!A2 -> INV-1201
A15: =revenue!B3 -> Oak & Pine Retail | B15: =revenue!C3 -> 36500 | D15: =revenue!A3 -> INV-1202
A16: =revenue!B4 -> Summit Fitness | B16: =revenue!C4 -> 52000 | D16: =revenue!A4 -> INV-1203
A17: =revenue!B5 -> Clearwater Legal | B17: =revenue!C5 -> 40000 | D17: =revenue!A5 -> INV-1204
A18: =accounting!A12 -> Other income | B18: =accounting!B12 -> 20000 | D18: =accounting!C12 -> Referral fee earned in December
A19: Total revenue | C19: =SUM(B14:B18) -> 196500
A20: Expenses
A21: =payroll!A2 -> Salaries expense | B21: =payroll!B2 -> 88000 | D21: =payroll!C2 -> Employee wages earned in December
A22: =payroll!A3 -> Payroll tax expense | B22: =payroll!B3 -> 7200 | D22: =payroll!C3 -> Employer payroll taxes
A23: =payroll!A4 -> Contractor expense | B23: =payroll!B4 -> 12500 | D23: =payroll!C4 -> Freelance design and copywriting
A24: =operations!A2 -> Office rent expense | B24: =operations!B2 -> 6000 | D24: =operations!C2 -> December office lease
A25: =operations!A3 -> Software subscriptions expense | B25: =operations!B3 -> 8400 | D25: =operations!C3 -> Marketing and analytics platforms
A26: =operations!A4 -> Advertising expense | B26: =operations!B4 -> 2500 | D26: =operations!C4 -> Blue Ridge Digital's own marketing
A27: =operations!A5 -> Utilities expense | B27: =operations!B5 -> 1200 | D27: =operations!C5 -> Internet, electricity, and phone
A28: =operations!A6 -> Insurance expense | B28: =operations!B6 -> 1800 | D28: =operations!C6 -> December portion of annual policy
A29: =accounting!A4 -> Depreciation expense | B29: =accounting!B4 -> 1100 | D29: =accounting!C4 -> December depreciation
A30: =accounting!A5 -> Interest expense | B30: =accounting!B5 -> 500 | D30: =accounting!C5 -> December loan interest
A31: Total expenses | C31: =SUM(B21:B30) -> 129200
A32: Net income | C32: =C19-C31 -> 67300

Sheet revenue
A1: Invoice ID | B1: Client | C1: December service revenue | D1: Cash collected | E1: Recognition note
A2: INV-1201 | B2: Harbor Dental Group | C2: 48000 | D2: 42000 | E2: December campaign services completed
A3: INV-1202 | B3: Oak & Pine Retail | C3: 36500 | D3: 36500 | E3: December retainer earned
A4: INV-1203 | B4: Summit Fitness | C4: 52000 | D4: 30000 | E4: December project milestone accepted
A5: INV-1204 | B5: Clearwater Legal | C5: 40000 | D5: 40000 | E5: December retainer earned
A6: INV-1205 | B6: New client deposit | C6: 20000 | D6: 20000 | E6: January work; not earned in December

Sheet payroll
A1: Account | B1: December actual | C1: Description
A2: Salaries expense | B2: 88000 | C2: Employee wages earned in December
A3: Payroll tax expense | B3: 7200 | C3: Employer payroll taxes
A4: Contractor expense | B4: 12500 | C4: Freelance design and copywriting
A5: Accrued payroll | B5: 9100 | C5: Wages earned but unpaid at month-end
A6: Employee advances | B6: 2500 | C6: Amounts recoverable from employees

Sheet operations
A1: Account | B1: December actual | C1: Description
A2: Office rent expense | B2: 6000 | C2: December office lease
A3: Software subscriptions expense | B3: 8400 | C3: Marketing and analytics platforms
A4: Advertising expense | B4: 2500 | C4: Blue Ridge Digital's own marketing
A5: Utilities expense | B5: 1200 | C5: Internet, electricity, and phone
A6: Insurance expense | B6: 1800 | C6: December portion of annual policy
A7: Office supplies | B7: 4800 | C7: Unused supplies on hand at December 31
A8: Prepaid insurance | B8: 19800 | C8: Unexpired portion of annual policy
A9: Computer equipment | B9: 72000 | C9: Equipment owned at December 31
A10: Accounts payable | B10: 36200 | C10: Unpaid vendor invoices
A11: Cash | B11: 300000 | C11: Bank balance at December 31

Sheet budget
A1: Account | B1: December budget | C1: Description
A2: Service revenue | B2: 190000 | C2: Planned revenue
A3: Salaries expense | B3: 85000 | C3: Planned salary expense
A4: Payroll tax expense | B4: 7000 | C4: Planned employer taxes
A5: Contractor expense | B5: 10000 | C5: Planned contractor expense
A6: Office rent expense | B6: 6000 | C6: Planned rent
A7: Software subscriptions expense | B7: 8000 | C7: Planned software expense
A8: Advertising expense | B8: 3000 | C8: Planned company advertising
A9: Utilities expense | B9: 1100 | C9: Planned utilities

Sheet accounting
A1: Account | B1: Balance | C1: Description
A2: Accounts receivable | B2: 174000 | C2: Amounts due from clients
A3: Accumulated depreciation | B3: 18500 | C3: Contra-asset balance
A4: Depreciation expense | B4: 1100 | C4: December depreciation
A5: Interest expense | B5: 500 | C5: December loan interest
A6: Unearned revenue | B6: 20000 | C6: Deposit for January services
A7: Note payable | B7: 65000 | C7: Outstanding loan principal
A8: Common stock | B8: 100000 | C8: Owner capital contribution
A9: Retained earnings | B9: 242700 | C9: Cumulative earnings before December close
A10: Owner distribution | B10: 10000 | C10: Distribution paid to owner
A11: Service revenue control total | B11: 176500 | C11: Earned December invoices from revenue tab
A12: Other income | B12: 20000 | C12: Referral fee earned in December
A13: Income taxes payable | B13: 4000 | C13: Estimated taxes owed
