Workbook

Sheet Exercise
A2: Blue Ridge Digital LLC — Balance Sheet Practice
A4: Reporting date | B4: December 31, 2026
A6: Task
A7: Use the five source tabs to prepare the balance sheet at December 31, 2026.
A8: Classify accounts as assets, liabilities, or stockholders’ equity.
A9: Present accumulated depreciation as a deduction from computer equipment.
A10: Determine retained earnings and verify that assets equal liabilities plus equity.
A11: Use actual ending balances only. Exclude income-statement, activity, and budget figures.
A13: Assets | B13: Amount | D13: Liabilities and Stockholders’ Equity | E13: Amount
A14: Current assets | D14: Current liabilities
A15: =assets!A2 -> Cash | B15: =assets!B2 -> 319200 | D15: =liabilities!A2 -> Accounts payable | E15: =liabilities!B2 -> 36200
A16: =assets!A3 -> Accounts receivable | B16: =assets!B3 -> 174000 | D16: =liabilities!A3 -> Accrued payroll | E16: =liabilities!B3 -> 9100
A17: =assets!A4 -> Office supplies | B17: =assets!B4 -> 4800 | D17: =liabilities!A4 -> Unearned revenue | E17: =liabilities!B4 -> 20000
A18: =assets!A5 -> Prepaid insurance | B18: =assets!B5 -> 19800 | D18: =liabilities!A5 -> Income taxes payable | E18: =liabilities!B5 -> 4000
D19: =liabilities!A6 -> Note payable | E19: =liabilities!B6 -> 65000
A21: Total current assets | B21: =SUM(B15:B18) -> 517800 | D21: Total current liabilities | E21: =SUM(E15:E19) -> 134300
A22: Property and equipment | D22: Long-term liabilities
A23: =assets!A6 -> Computer equipment | B23: =assets!B6 -> 72000
D24: Total liabilities
A26: Net property and equipment | B26: =SUM(B23:B24) -> 72000 | D26: Stockholders’ equity
D27: =equity!A2 -> Common stock | E27: =equity!B2 -> 145000
A28: Total assets | B28: =B21+B26 -> 589800 | D28: =equity!A3 -> Retained earnings | E28: =B28-(E21+E27) -> 310500
D32: Total stockholders’ equity | E32: =SUM(E27:E31) -> 455500
D33: Total liabilities and equity | E33: =E32+E21 -> 589800

Sheet assets
A1: Account or metric | B1: December 31, 2026 | C1: Description
A2: Cash | B2: 319200 | C2: Ending bank balance
A3: Accounts receivable | B3: 174000 | C3: Amounts due from customers
A4: Office supplies | B4: 4800 | C4: Unused supplies on hand
A5: Prepaid insurance | B5: 19800 | C5: Unexpired insurance coverage
A6: Computer equipment | B6: 72000 | C6: Equipment cost before accumulated depreciation
A7: Accumulated depreciation | B7: 18500 | C7: Contra-asset; deduct from computer equipment
A8: Cash collected from customers | B8: 2290000 | C8: 2026 cash receipts; activity, not an ending asset balance
A9: Equipment purchased during 2026 | B9: 24000 | C9: Capital expenditure already reflected in equipment balance
A10: Depreciation expense | B10: 1100 | C10: Income-statement account

Sheet liabilities
A1: Account or metric | B1: December 31, 2026 | C1: Description
A2: Accounts payable | B2: 36200 | C2: Unpaid vendor invoices
A3: Accrued payroll | B3: 9100 | C3: Employee compensation owed
A4: Unearned revenue | B4: 20000 | C4: Customer deposits for future services
A5: Income taxes payable | B5: 4000 | C5: Taxes owed at year-end
A6: Note payable | B6: 65000 | C6: Outstanding long-term loan principal
A7: Bank loan proceeds | B7: 80000 | C7: 2026 borrowing activity; not the ending liability balance
A8: Principal repaid | B8: 10000 | C8: 2026 financing activity
A9: Interest expense | B9: 4200 | C9: Income-statement account
A10: Customer deposits received | B10: 15000 | C10: 2026 cash receipts already reflected in unearned revenue

Sheet equity
A1: Account or metric | B1: Amount | C1: Description
A2: Common stock | B2: 145000 | C2: Ending common stock balance
A3: Retained earnings | C3: Determine the ending balance
A4: Beginning retained earnings | B4: 242700 | C4: Balance at January 1, 2026
A5: Net income | B5: 67300 | C5: 2026 earnings
A6: Dividends | B6: 18000 | C6: 2026 distributions to stockholders
A7: Common stock issued | B7: 45000 | C7: 2026 issuance already reflected in ending common stock
A8: Total stockholders’ equity | B8: 437000 | C8: Independent control total from the equity statement
A9: Owner salary | B9: 15000 | C9: Compensation expense, not an equity distribution

Sheet income_statement
A1: Account | B1: 2026 actual | C1: Description
A2: Service revenue | B2: 2358000 | C2: Income-statement account
A3: Other income | B3: 22000 | C3: Income-statement account
A4: Operating expenses | B4: 2248500 | C4: Income-statement account
A5: Interest expense | B5: 4200 | C5: Income-statement account
A6: Income tax expense | B6: 60000 | C6: Income-statement account
A7: Net income | B7: 67300 | C7: Flows into retained earnings; do not list separately on balance sheet
A8: Cash collected | B8: 2290000 | C8: Cash-flow activity

Sheet budget
A1: Account | B1: 2026 budget | C1: Description
A2: Cash | B2: 350000 | C2: Budgeted ending cash
A3: Accounts receivable | B3: 160000 | C3: Budgeted ending receivables
A4: Accounts payable | B4: 30000 | C4: Budgeted ending payables
A5: Note payable | B5: 70000 | C5: Budgeted ending debt
A6: Common stock | B6: 160000 | C6: Budgeted ending common stock
A7: Retained earnings | B7: 310000 | C7: Budgeted ending retained earnings
A8: Net income | B8: 95000 | C8: Budgeted annual earnings
